{
  "formatVersion": 1,
  "database": {
    "version": 1,
    "identityHash": "93fc04c9221c1eb7cedc2197bd545c2a",
    "entities": [
      {
        "tableName": "categories",
        "createSql": "CREATE TABLE IF NOT EXISTS `${TABLE_NAME}` (`id` INTEGER PRIMARY KEY AUTOINCREMENT NOT NULL, `name` TEXT NOT NULL, `icon_res_name` TEXT NOT NULL, `type` TEXT NOT NULL, `color` INTEGER NOT NULL)",
        "fields": [
          {
            "fieldPath": "id",
            "columnName": "id",
            "affinity": "INTEGER",
            "notNull": true
          },
          {
            "fieldPath": "name",
            "columnName": "name",
            "affinity": "TEXT",
            "notNull": true
          },
          {
            "fieldPath": "iconResName",
            "columnName": "icon_res_name",
            "affinity": "TEXT",
            "notNull": true
          },
          {
            "fieldPath": "type",
            "columnName": "type",
            "affinity": "TEXT",
            "notNull": true
          },
          {
            "fieldPath": "color",
            "columnName": "color",
            "affinity": "INTEGER",
            "notNull": true
          }
        ],
        "primaryKey": {
          "autoGenerate": true,
          "columnNames": [
            "id"
          ]
        },
        "indices": [],
        "foreignKeys": []
      },
      {
        "tableName": "transactions",
        "createSql": "CREATE TABLE IF NOT EXISTS `${TABLE_NAME}` (`id` INTEGER PRIMARY KEY AUTOINCREMENT NOT NULL, `type` TEXT NOT NULL, `amount` REAL NOT NULL, `category_id` INTEGER NOT NULL DEFAULT 1, `timestamp` INTEGER NOT NULL, `note` TEXT NOT NULL, `image_uri` TEXT, FOREIGN KEY(`category_id`) REFERENCES `categories`(`id`) ON UPDATE NO ACTION ON DELETE SET DEFAULT )",
        "fields": [
          {
            "fieldPath": "id",
            "columnName": "id",
            "affinity": "INTEGER",
            "notNull": true
          },
          {
            "fieldPath": "type",
            "columnName": "type",
            "affinity": "TEXT",
            "notNull": true
          },
          {
            "fieldPath": "amount",
            "columnName": "amount",
            "affinity": "REAL",
            "notNull": true
          },
          {
            "fieldPath": "categoryId",
            "columnName": "category_id",
            "affinity": "INTEGER",
            "notNull": true,
            "defaultValue": "1"
          },
          {
            "fieldPath": "timestamp",
            "columnName": "timestamp",
            "affinity": "INTEGER",
            "notNull": true
          },
          {
            "fieldPath": "note",
            "columnName": "note",
            "affinity": "TEXT",
            "notNull": true
          },
          {
            "fieldPath": "imageUri",
            "columnName": "image_uri",
            "affinity": "TEXT",
            "notNull": false
          }
        ],
        "primaryKey": {
          "autoGenerate": true,
          "columnNames": [
            "id"
          ]
        },
        "indices": [
          {
            "name": "index_transactions_category_id",
            "unique": false,
            "columnNames": [
              "category_id"
            ],
            "orders": [],
            "createSql": "CREATE INDEX IF NOT EXISTS `index_transactions_category_id` ON `${TABLE_NAME}` (`category_id`)"
          },
          {
            "name": "index_transactions_timestamp",
            "unique": false,
            "columnNames": [
              "timestamp"
            ],
            "orders": [],
            "createSql": "CREATE INDEX IF NOT EXISTS `index_transactions_timestamp` ON `${TABLE_NAME}` (`timestamp`)"
          }
        ],
        "foreignKeys": [
          {
            "table": "categories",
            "onDelete": "SET DEFAULT",
            "onUpdate": "NO ACTION",
            "columns": [
              "category_id"
            ],
            "referencedColumns": [
              "id"
            ]
          }
        ]
      }
    ],
    "views": [],
    "setupQueries": [
      "CREATE TABLE IF NOT EXISTS room_master_table (id INTEGER PRIMARY KEY,identity_hash TEXT)",
      "INSERT OR REPLACE INTO room_master_table (id,identity_hash) VALUES(42, '93fc04c9221c1eb7cedc2197bd545c2a')"
    ]
  }
}